promptlifter/__init__.py
promptlifter/config.py
promptlifter/conversation_llm.py
promptlifter/logging_config.py
promptlifter/main.py
promptlifter/context/__init__.py
promptlifter/context/context_optimizer.py
promptlifter/context/context_retriever.py
promptlifter/context/conversation_manager.py
promptlifter/context/query_classifier.py
promptlifter/nodes/__init__.py
promptlifter/nodes/embedding_service.py
promptlifter/nodes/llm_service.py
promptlifter/nodes/run_pinecone_search.py
promptlifter/nodes/run_tavily_search.py
promptlifter-0.5.0.dist-info/licenses/LICENSE
promptlifter-0.5.0.dist-info/METADATA
promptlifter-0.5.0.dist-info/WHEEL
promptlifter-0.5.0.dist-info/entry_points.txt
promptlifter-0.5.0.dist-info/top_level.txt
promptlifter-0.5.0.dist-info/RECORD
