Metadata-Version: 2.4
Name: promptlifter
Version: 0.5.0
Summary: LLM-powered conversation interface with intelligent context management, real-time search integration, and seamless conversation flow
Home-page: https://github.com/Thinkata/promptlifter
Author: PromptLifter Team
Author-email: PromptLifter Team <promptlifter@thinkata.com>
Maintainer-email: PromptLifter Team <promptlifter@thinkata.com>
License: MIT
Project-URL: Homepage, https://github.com/Thinkata/promptlifter
Project-URL: Repository, https://github.com/Thinkata/promptlifter
Project-URL: Documentation, https://github.com/Thinkata/promptlifter#readme
Project-URL: Changelog, https://github.com/Thinkata/promptlifter/blob/main/CHANGELOG.md
Project-URL: Bug Reports, https://github.com/Thinkata/promptlifter/issues
Project-URL: Source Code, https://github.com/Thinkata/promptlifter
Keywords: llm,conversation,ai,machine-learning,context-management,search,vector-search,chatbot,tavily,pinecone,ollama,openai,anthropic,real-time-search,conversation-flow
Classifier: Development Status :: 3 - Alpha
Classifier: Intended Audience :: Developers
Classifier: Intended Audience :: Science/Research
Classifier: Operating System :: OS Independent
Classifier: Programming Language :: Python :: 3
Classifier: Programming Language :: Python :: 3.13
Classifier: Topic :: Scientific/Engineering :: Artificial Intelligence
Classifier: Topic :: Software Development :: Libraries :: Python Modules
Classifier: Topic :: Text Processing :: Linguistic
Classifier: Topic :: Internet :: WWW/HTTP :: Dynamic Content
Requires-Python: >=3.9
License-File: LICENSE
Requires-Dist: httpx>=0.24.0
Requires-Dist: python-dotenv>=1.0.0
Requires-Dist: openai>=1.0.0
Requires-Dist: anthropic>=0.18.0
Requires-Dist: google-generativeai>=0.3.0
Requires-Dist: pinecone>=7.3.0
Requires-Dist: tavily-python>=0.3.0
Provides-Extra: dev
Requires-Dist: pytest>=7.0.0; extra == "dev"
Requires-Dist: pytest-asyncio>=0.21.0; extra == "dev"
Requires-Dist: pytest-cov>=4.0.0; extra == "dev"
Requires-Dist: black>=22.0.0; extra == "dev"
Requires-Dist: flake8>=5.0.0; extra == "dev"
Requires-Dist: isort>=5.0.0; extra == "dev"
Requires-Dist: mypy>=1.0.0; extra == "dev"
Requires-Dist: pre-commit>=3.0.0; extra == "dev"
Requires-Dist: tox>=4.0.0; extra == "dev"
Requires-Dist: build>=1.0.0; extra == "dev"
Requires-Dist: twine>=4.0.0; extra == "dev"
Provides-Extra: test
Requires-Dist: pytest>=7.0.0; extra == "test"
Requires-Dist: pytest-asyncio>=0.21.0; extra == "test"
Requires-Dist: pytest-cov>=4.0.0; extra == "test"
Dynamic: author
Dynamic: home-page
Dynamic: license-file
Dynamic: requires-python
